Workbook
Name _xlchart.v1.0: 'продажи'!$O$1
Name _xlchart.v1.1: 'продажи'!$O$2:$O$1001

Sheet интро
C3: Исследование выполнила: Алексеева Анастасия
C4: Данные сгенерированы ChatGPT и не являются NDA
C6: Задачи исследования | D6: № | E6: Декомпозиция | F6: Выводы исследования
C7: Анализ продаж продуктовых сетей | D7: 1 | E7: Динамика продаж по магазинам | F7: Вывод описан в примечании
D8: 2 | E8: Анализ цен внутри товарной категории по магазинам | F8: Вывод описан в примечании
D9: 3 | E9: Суммарные продажи по магазинам | F9: Вывод описан в примечании
C10: Сравнение поставщиков по объемам закупок | D10: 4 | E10: Анализ цен внутри категории по поставщикам | F10: Вывод описан в примечании
D11: 5 | E11: Суммарные продажи по поставщикам | F11: Вывод описан в примечании
C12: Изучение продаж по категориям товаров | D12: 6 | E12: Суммарные продажи по категориям | F12: Вывод описан в примечании
D13: 7 | E13: Среднее кол-во по категориям (что покупают чаще) | F13: Вывод описан в примечании
C14: Изучение клиентов по географии и лайфтайму | D14: 8 | E14: Аналитика географии клиентов | F14: Вывод описан в примечании
D15: 9 | E15: Кол-во клиентов в программе лояльности | F15: Вывод описан в примечании
D16: 10 | E16: Кол-во дней с момента регистрации до покупки | F16: Вывод описан в примечании
D17: 11 | E17: Лайфтайм клиента | F17: Вывод описан в примечании
D18: 12 | E18: Частотность имен для рекламной компании | F18: Вывод описан в примечании
D19: 13 | E19: Платежеспособность по странам | F19: Вывод описан в примечании
C21: Отработка Hard Skills
C22: Преобразование типов и визуальное форматирование
C23: Условное форматирование данных
C24: Умные таблицы и работа с абсолютными и относительными ссылками
C25: Математические и текстовые функции
C26: Функции для работы с датой и временем
C27: Функции поиска и извлечения данных
C28: Сводные таблицы и срезы данных
C29: Построение диаграмм

Sheet Дашборды

Sheet Выгода клиентам
A3: Названия строк | B3: Среднее по полю Выгода для клиента
A4: Лента | B4: 0.10062699
A5: Седьмой Континент | B5: 0.081840255
A6: Городской Супермаркет | B6: 0.05896841
A7: Билла | B7: 0.056287666
A8: Метро | B8: 0.047135773
A9: Азбука Вкуса | B9: 0.036131084
A10: Мосмарт | B10: 0.023330794
A11: Мираторг | B11: 0.010296277
A12: Карусель | B12: 0.0070069985
A13: Ароматный Мир | B13: 0.0052821685
A14: Бристоль | B14: -0.0080940543
A15: Дикси | B15: -0.009488577
... A23: Пятерочка | B23: -0.10170732

Sheet Продажи магазинов 

Sheet Суммарные продажи по магазинам
A3: Продуктовая сеть | B3: GMV
A4: О'кей | B4: 264220
A5: Гиперглобус | B5: 258945
A6: Мосмарт | B6: 247900
A7: Спар | B7: 243730
A8: Верный | B8: 235140
A9: Городской Супермаркет | B9: 215490
A10: Ароматный Мир | B10: 214185
A11: Седьмой Континент | B11: 205530
A12: Бристоль | B12: 205050
A13: Мираторг | B13: 200145
A14: Метро | B14: 195840
A15: Лента | B15: 191560
... A23: Билла | B23: 136375

Sheet Средняя цена по поставщикам
A3: Названия строк | B3: Среднее по полю Средняя стоимость в категории по поставщику
A4: Green Garden | B4: 369.2
A5: Каравай | B5: 331.16667
A6: Макфа | B6: 329.27273
A7: КДВ | B7: 323.07692
A8: Беллакт | B8: 322.54545
A9: Посиделкино | B9: 321.63636
A10: Экстра | B10: 320.84615
A11: Lay's | B11: 320.57143
A12: Черкизово | B12: 320.25
A13: Простоквашино | B13: 318.81818
A14: Агро-Альянс | B14: 317.85714
A15: Русский Хлеб | B15: 316.6
... A81: Микоян | B81: 82

Sheet Суммарн продажи по поставщикам
A3: Поставщик | B3: Суммарные продажи
A4: Паста Зара | B4: 147150
A5: Фруктовый сад | B5: 124360
A6: Сырная долина | B6: 121000
A7: Greenfield | B7: 105955
A8: Бабаевский | B8: 102310
A9: Борилла | B9: 101725
A10: Домик в деревне | B10: 93695
A11: Pringles | B11: 91840
A12: Белый Злат | B12: 87355
A13: Рот Фронт | B13: 84370
A14: Jacobs | B14: 78755
A15: Овощной ряд | B15: 77905
... A81: Микоян | B81: 410

Sheet Среднее кол-во по категории
A3: Названия строк | B3: Среднее по полю кол-во штук в чеке
A4: Йогурт | B4: 2.7627119
A5: Колбаса | B5: 2.8846154
A6: Конфеты | B6: 2.983871
A7: Кофе | B7: 3.047619
A8: Крупа | B8: 2.7209302
A9: Макароны | B9: 2.9418605
A10: Молоко | B10: 3.2380952
A11: Мясо | B11: 3.1272727
A12: Овощи | B12: 3.1463415
A13: Печенье | B13: 3.0638298
A14: Рис | B14: 3.1875
A15: Рыба | B15: 3.1282051
... A23: Чипсы | B23: 3.0588235

Sheet Лайфтайм клиента

Sheet Суммарные продажи по категориям

Sheet Платежеспособность

Sheet продажи
A1: id чека | B1: id товара | C1: цена за шт в рублях | D1: кол-во штук в чеке | E1: Сумма чека | F1: дата создания чека | G1: магазин покупки | H1: id клиента | I1: Категория товара | J1: Средняя цена в категории за шт | K1: Выгода для клиента | L1: Поставщик товара | M1: Средняя стоимость в категории по поставщику | N1: Дата регистрации клиента | O1: Кол-во дней с момента регистрации | P1: Страна клиента | Q1: Текущая дата | R1: Лайфтайм клиента
A2: 1 | B2: 300 | C2: 103 | D2: 4 | E2: =C2*D2 -> 412 | F2: 45187 | G2: Бристоль | H2: 315 | I2: =VLOOKUP(B2,'товар'!$A$1:$C$433,2,FALSE) -> Сахар | J2: =AVERAGEIF($I$2:$I$1001,I2,$C$2:$C$1001) -> 252.76271 | K2: =C2/J2-1 -> -0.59250319 | L2: =VLOOKUP(B2,'товар'!$A$1:$C$433,3,FALSE) -> Продимекс | M2: =AVERAGEIFS($C$2:$C$1001,$I$2:$I$1001,I2,$L$2:$L$1001,L2) -> 240.5 | N2: =VLOOKUP(H2,'клиенты'!$A$1:$F$435,5,FALSE) -> 44747 | O2: =F2-N2 -> 440 | P2: =VLOOKUP(H2,'клиенты'!$A$2:$J$435,10,FALSE) -> Узбекистан | Q2: =NOW() -> 46078.459 | R2: =(Q2-N2)/30 -> 44.381967
A3: 2 | B3: 486 | C3: 296 | D3: 3 | E3: =C3*D3 -> 888 | F3: 45083 | G3: Дикси | H3: 253 | I3: =VLOOKUP(B3,'товар'!$A$1:$C$433,2,FALSE) -> Соль | J3: =AVERAGEIF($I$2:$I$1001,I3,$C$2:$C$1001) -> 264.86792 | K3: =C3/J3-1 -> 0.11753811 | L3: =VLOOKUP(B3,'товар'!$A$1:$C$433,3,FALSE) -> Илецкая | M3: =AVERAGEIFS($C$2:$C$1001,$I$2:$I$1001,I3,$L$2:$L$1001,L3) -> 238.16667 | N3: =VLOOKUP(H3,'клиенты'!$A$1:$F$435,5,FALSE) -> 44750 | O3: =F3-N3 -> 333 | P3: =VLOOKUP(H3,'клиенты'!$A$2:$J$435,10,FALSE) -> Беларусь | Q3: =NOW() -> 46078.459 | R3: =(Q3-N3)/30 -> 44.281967
A4: 3 | B4: 76 | C4: 139 | D4: 5 | E4: =C4*D4 -> 695 | F4: 45363 | G4: Городской Супермаркет | H4: 12 | I4: =VLOOKUP(B4,'товар'!$A$1:$C$433,2,FALSE) -> Печенье | J4: =AVERAGEIF($I$2:$I$1001,I4,$C$2:$C$1001) -> 283.46809 | K4: =C4/J4-1 -> -0.50964497 | L4: =VLOOKUP(B4,'товар'!$A$1:$C$433,3,FALSE) -> Юбилейное | M4: =AVERAGEIFS($C$2:$C$1001,$I$2:$I$1001,I4,$L$2:$L$1001,L4) -> 232.44444 | N4: =VLOOKUP(H4,'клиенты'!$A$1:$F$435,5,FALSE) -> 44842 | O4: =F4-N4 -> 521 | P4: =VLOOKUP(H4,'клиенты'!$A$2:$J$435,10,FALSE) -> Беларусь | Q4: =NOW() -> 46078.459 | R4: =(Q4-N4)/30 -> 41.2153
A5: 4 | B5: 240 | C5: 141 | D5: 5 | E5: =C5*D5 -> 705 | F5: 45262 | G5: Верный | H5: 116 | I5: =VLOOKUP(B5,'товар'!$A$1:$C$433,2,FALSE) -> Макароны | J5: =AVERAGEIF($I$2:$I$1001,I5,$C$2:$C$1001) -> 265.47674 | K5: =C5/J5-1 -> -0.46888003 | L5: =VLOOKUP(B5,'товар'!$A$1:$C$433,3,FALSE) -> Борилла | M5: =AVERAGEIFS($C$2:$C$1001,$I$2:$I$1001,I5,$L$2:$L$1001,L5) -> 236.27586 | N5: =VLOOKUP(H5,'клиенты'!$A$1:$F$435,5,FALSE) -> 44643 | O5: =F5-N5 -> 619 | P5: =VLOOKUP(H5,'клиенты'!$A$2:$J$435,10,FALSE) -> Россия | Q5: =NOW() -> 46078.459 | R5: =(Q5-N5)/30 -> 47.848634
A6: 5 | B6: 32 | C6: 123 | D6: 2 | E6: =C6*D6 -> 246 | F6: 45151 | G6: Спар | H6: 471 | I6: =VLOOKUP(B6,'товар'!$A$1:$C$433,2,FALSE) -> Овощи | J6: =AVERAGEIF($I$2:$I$1001,I6,$C$2:$C$1001) -> 250.4878 | K6: =C6/J6-1 -> -0.50895813 | L6: =VLOOKUP(B6,'товар'!$A$1:$C$433,3,FALSE) -> Зеленая грядка | M6: =AVERAGEIFS($C$2:$C$1001,$I$2:$I$1001,I6,$L$2:$L$1001,L6) -> 159.2 | N6: =VLOOKUP(H6,'клиенты'!$A$1:$F$435,5,FALSE) -> 44577 | O6: =F6-N6 -> 574 | P6: =VLOOKUP(H6,'клиенты'!$A$2:$J$435,10,FALSE) -> Украина | Q6: =NOW() -> 46078.459 | R6: =(Q6-N6)/30 -> 50.048634
A7: 6 | B7: 162 | C7: 452 | D7: 2 | E7: =C7*D7 -> 904 | F7: 45281 | G7: Бристоль | H7: 374 | I7: =VLOOKUP(B7,'товар'!$A$1:$C$433,2,FALSE) -> Сок | J7: =AVERAGEIF($I$2:$I$1001,I7,$C$2:$C$1001) -> 268.60345 | K7: =C7/J7-1 -> 0.6827781 | L7: =VLOOKUP(B7,'товар'!$A$1:$C$433,3,FALSE) -> Фруктовый сад | M7: =AVERAGEIFS($C$2:$C$1001,$I$2:$I$1001,I7,$L$2:$L$1001,L7) -> 281.96875 | N7: =VLOOKUP(H7,'клиенты'!$A$1:$F$435,5,FALSE) -> 44582 | O7: =F7-N7 -> 699 | P7: =VLOOKUP(H7,'клиенты'!$A$2:$J$435,10,FALSE) -> Украина | Q7: =NOW() -> 46078.459 | R7: =(Q7-N7)/30 -> 49.881967
A8: 7 | B8: 323 | C8: 149 | D8: 5 | E8: =C8*D8 -> 745 | F8: 45349 | G8: Карусель | H8: 477 | I8: =VLOOKUP(B8,'товар'!$A$1:$C$433,2,FALSE) -> Рыба | J8: =AVERAGEIF($I$2:$I$1001,I8,$C$2:$C$1001) -> 258.51282 | K8: =C8/J8-1 -> -0.42362626 | L8: =VLOOKUP(B8,'товар'!$A$1:$C$433,3,FALSE) -> Меридиан | M8: =AVERAGEIFS($C$2:$C$1001,$I$2:$I$1001,I8,$L$2:$L$1001,L8) -> 260.64706 | N8: =VLOOKUP(H8,'клиенты'!$A$1:$F$435,5,FALSE) -> 44738 | O8: =F8-N8 -> 611 | P8: =VLOOKUP(H8,'клиенты'!$A$2:$J$435,10,FALSE) -> Узбекистан | Q8: =NOW() -> 46078.459 | R8: =(Q8-N8)/30 -> 44.681967
A9: 8 | B9: 60 | C9: 489 | D9: 4 | E9: =C9*D9 -> 1956 | F9: 45327 | G9: Мираторг | H9: 335 | I9: =VLOOKUP(B9,'товар'!$A$1:$C$433,2,FALSE) -> Кофе | J9: =AVERAGEIF($I$2:$I$1001,I9,$C$2:$C$1001) -> 249.02381 | K9: =C9/J9-1 -> 0.96366765 | L9: =VLOOKUP(B9,'товар'!$A$1:$C$433,3,FALSE) -> Jacobs | M9: =AVERAGEIFS($C$2:$C$1001,$I$2:$I$1001,I9,$L$2:$L$1001,L9) -> 276.21053 | N9: =VLOOKUP(H9,'клиенты'!$A$1:$F$435,5,FALSE) -> 44619 | O9: =F9-N9 -> 708 | P9: =VLOOKUP(H9,'клиенты'!$A$2:$J$435,10,FALSE) -> Узбекистан | Q9: =NOW() -> 46078.459 | R9: =(Q9-N9)/30 -> 48.648634
A10: 9 | B10: 401 | C10: 416 | D10: 5 | E10: =C10*D10 -> 2080 | F10: 45376 | G10: Мосмарт | H10: 350 | I10: =VLOOKUP(B10,'товар'!$A$1:$C$433,2,FALSE) -> Чай | J10: =AVERAGEIF($I$2:$I$1001,I10,$C$2:$C$1001) -> 271.18182 | K10: =C10/J10-1 -> 0.53402615 | L10: =VLOOKUP(B10,'товар'!$A$1:$C$433,3,FALSE) -> Greenfield | M10: =AVERAGEIFS($C$2:$C$1001,$I$2:$I$1001,I10,$L$2:$L$1001,L10) -> 291.45455 | N10: =VLOOKUP(H10,'клиенты'!$A$1:$F$435,5,FALSE) -> 44684 | O10: =F10-N10 -> 692 | P10: =VLOOKUP(H10,'клиенты'!$A$2:$J$435,10,FALSE) -> Украина | Q10: =NOW() -> 46078.459 | R10: =(Q10-N10)/30 -> 46.481967
A11: 10 | B11: 100 | C11: 449 | D11: 2 | E11: =C11*D11 -> 898 | F11: 45032 | G11: Карусель | H11: 413 | I11: =VLOOKUP(B11,'товар'!$A$1:$C$433,2,FALSE) -> Йогурт | J11: =AVERAGEIF($I$2:$I$1001,I11,$C$2:$C$1001) -> 263.25424 | K11: =C11/J11-1 -> 0.70557559 | L11: =VLOOKUP(B11,'товар'!$A$1:$C$433,3,FALSE) -> Ростагроэкспорт | M11: =AVERAGEIFS($C$2:$C$1001,$I$2:$I$1001,I11,$L$2:$L$1001,L11) -> 257.78261 | N11: =VLOOKUP(H11,'клиенты'!$A$1:$F$435,5,FALSE) -> 44699 | O11: =F11-N11 -> 333 | P11: =VLOOKUP(H11,'клиенты'!$A$2:$J$435,10,FALSE) -> Россия | Q11: =NOW() -> 46078.459 | R11: =(Q11-N11)/30 -> 45.981967
A12: 11 | B12: 217 | C12: 296 | D12: 2 | E12: =C12*D12 -> 592 | F12: 45136 | G12: Карусель | H12: 495 | I12: =VLOOKUP(B12,'товар'!$A$1:$C$433,2,FALSE) -> Мясо | J12: =AVERAGEIF($I$2:$I$1001,I12,$C$2:$C$1001) -> 271.74545 | K12: =C12/J12-1 -> 0.08925465 | L12: =VLOOKUP(B12,'товар'!$A$1:$C$433,3,FALSE) -> Агрокомплекс | M12: =AVERAGEIFS($C$2:$C$1001,$I$2:$I$1001,I12,$L$2:$L$1001,L12) -> 311.2 | N12: =VLOOKUP(H12,'клиенты'!$A$1:$F$435,5,FALSE) -> 44654 | O12: =F12-N12 -> 482 | P12: =VLOOKUP(H12,'клиенты'!$A$2:$J$435,10,FALSE) -> Узбекистан | Q12: =NOW() -> 46078.459 | R12: =(Q12-N12)/30 -> 47.481967
A13: 12 | B13: 445 | C13: 109 | D13: 5 | E13: =C13*D13 -> 545 | F13: 45394 | G13: Мираторг | H13: 353 | I13: =VLOOKUP(B13,'товар'!$A$1:$C$433,2,FALSE) -> Сахар | J13: =AVERAGEIF($I$2:$I$1001,I13,$C$2:$C$1001) -> 252.76271 | K13: =C13/J13-1 -> -0.56876551 | L13: =VLOOKUP(B13,'товар'!$A$1:$C$433,3,FALSE) -> Сладов | M13: =AVERAGEIFS($C$2:$C$1001,$I$2:$I$1001,I13,$L$2:$L$1001,L13) -> 240.26667 | N13: =VLOOKUP(H13,'клиенты'!$A$1:$F$435,5,FALSE) -> 44656 | O13: =F13-N13 -> 738 | P13: =VLOOKUP(H13,'клиенты'!$A$2:$J$435,10,FALSE) -> Таджикистан | Q13: =NOW() -> 46078.459 | R13: =(Q13-N13)/30 -> 47.4153
... A1001: 1000 | B1001: 296 | C1001: 453 | D1001: 1 | E1001: =C1001*D1001 -> 453 | F1001: 45265 | G1001: Мосмарт | H1001: 167 | I1001: =VLOOKUP(B1001,'товар'!$A$1:$C$433,2,FALSE) -> Крупа | J1001: =AVERAGEIF($I$2:$I$1001,I1001,$C$2:$C$1001) -> 255.11628 | K1001: =C1001/J1001-1 -> 0.77566089 | L1001: =VLOOKUP(B1001,'товар'!$A$1:$C$433,3,FALSE) -> Мистраль | M1001: =AVERAGEIFS($C$2:$C$1001,$I$2:$I$1001,I1001,$L$2:$L$1001,L1001) -> 250.30769 | N1001: =VLOOKUP(H1001,'клиенты'!$A$1:$F$435,5,FALSE) -> 44563 | O1001: =F1001-N1001 -> 702 | P1001: =VLOOKUP(H1001,'клиенты'!$A$2:$J$435,10,FALSE) -> Узбекистан | Q1001: =NOW() -> 46078.459 | R1001: =(Q1001-N1001)/30 -> 50.5153

Sheet товар
A1: id товара | B1: категория товара | C1: поставщик
A2: 300 | B2: Сахар | C2: Продимекс
A3: 486 | B3: Соль | C3: Илецкая
A4: 76 | B4: Печенье | C4: Юбилейное
A5: 240 | B5: Макароны | C5: Борилла
A6: 32 | B6: Овощи | C6: Зеленая грядка
A7: 162 | B7: Сок | C7: Фруктовый сад
A8: 323 | B8: Рыба | C8: Меридиан
A9: 60 | B9: Кофе | C9: Jacobs
A10: 401 | B10: Чай | C10: Greenfield
A11: 100 | B11: Йогурт | C11: Ростагроэкспорт
A12: 217 | B12: Мясо | C12: Агрокомплекс
A13: 445 | B13: Сахар | C13: Сладов
... A433: 469 | B433: Сахар | C433: Сладов

Sheet Клиенты в программе лояльности
A3: Количество по полю ФИО | B3: Названия столбцов
A4: Названия строк | B4: да | C4: нет
A5: Беларусь | B5: 26 | C5: 25
A6: Россия | B6: 73 | C6: 73
A7: Таджикистан | B7: 36 | C7: 38
A8: Узбекистан | B8: 40 | C8: 45
A9: Украина | B9: 40 | C9: 38

Sheet География клиентов
A3: Названия строк | B3: Количество по полю id клиента
A4: Россия | B4: 146
A5: Узбекистан | B5: 85
A6: Украина | B6: 78
A7: Таджикистан | B7: 74
A8: Беларусь | B8: 51

Sheet клиенты
A1: id клиента | B1: номер телефона клиента | C1: ФИО | D1: Программа лояльности клиента | E1: Дата регистрации клиента | F1: Коды телефона | G1: Имя | H1: Фамилия | I1: Отчество | J1: Страна
A2: 315 | B2: +998 469-847-6587 | C2: Фадей Ефимович Калинин | D2: да | E2: 44747 | F2: =LEFT(B2,LEN(B2) - 13) -> +998 | G2: Фадей | H2: Ефимович | I2: Калинин | J2: {=XLOOKUP(F2,'коды стран'!$B$2:$B$7,'коды стран'!$A$2:$A$7)} -> Узбекистан
A3: 253 | B3: +375 796-304-7865 | C3: Вера Георгиевна Некрасова | D3: да | E3: 44750 | F3: =LEFT(B3,LEN(B3) - 13) -> +375 | G3: Вера | H3: Георгиевна | I3: Некрасова | J3: {=XLOOKUP(F3,'коды стран'!$B$2:$B$7,'коды стран'!$A$2:$A$7)} -> Беларусь
A4: 12 | B4: +375 682-373-1802 | C4: Никодим Игоревич Бобров | D4: да | E4: 44842 | F4: =LEFT(B4,LEN(B4) - 13) -> +375 | G4: Никодим | H4: Игоревич | I4: Бобров | J4: {=XLOOKUP(F4,'коды стран'!$B$2:$B$7,'коды стран'!$A$2:$A$7)} -> Беларусь
A5: 116 | B5: +7 753-596-5037 | C5: Носкова Вера Федоровна | D5: нет | E5: 44643 | F5: =LEFT(B5,LEN(B5) - 13) -> +7 | G5: Вера | H5: Федоровна | I5: Носкова | J5: {=XLOOKUP(F5,'коды стран'!$B$2:$B$7,'коды стран'!$A$2:$A$7)} -> Россия
A6: 471 | B6: +380 669-437-2066 | C6: Александра Матвеевна Артемьева | D6: да | E6: 44577 | F6: =LEFT(B6,LEN(B6) - 13) -> +380 | G6: Александра | H6: Матвеевна | I6: Артемьева | J6: {=XLOOKUP(F6,'коды стран'!$B$2:$B$7,'коды стран'!$A$2:$A$7)} -> Украина
A7: 374 | B7: +380 622-144-1703 | C7: Калинина Ирина Филипповна | D7: нет | E7: 44582 | F7: =LEFT(B7,LEN(B7) - 13) -> +380 | G7: Ирина | H7: Филипповна | I7: Калинина | J7: {=XLOOKUP(F7,'коды стран'!$B$2:$B$7,'коды стран'!$A$2:$A$7)} -> Украина
A8: 477 | B8: +998 591-865-8342 | C8: Зоя Кирилловна Брагина | D8: да | E8: 44738 | F8: =LEFT(B8,LEN(B8) - 13) -> +998 | G8: Зоя | H8: Кирилловна | I8: Брагина | J8: {=XLOOKUP(F8,'коды стран'!$B$2:$B$7,'коды стран'!$A$2:$A$7)} -> Узбекистан
A9: 335 | B9: +998 353-736-8172 | C9: Осипов Светозар Ефремович | D9: нет | E9: 44619 | F9: =LEFT(B9,LEN(B9) - 13) -> +998 | G9: Осипов | H9: Светозар | I9: Ефремович | J9: {=XLOOKUP(F9,'коды стран'!$B$2:$B$7,'коды стран'!$A$2:$A$7)} -> Узбекистан
A10: 350 | B10: +380 545-746-8707 | C10: Любовь Георгиевна Мамонтова | D10: нет | E10: 44684 | F10: =LEFT(B10,LEN(B10) - 13) -> +380 | G10: Любовь | H10: Георгиевна | I10: Мамонтова | J10: {=XLOOKUP(F10,'коды стран'!$B$2:$B$7,'коды стран'!$A$2:$A$7)} -> Украина
A11: 413 | B11: +7 063-931-5918 | C11: Август Вячеславович Брагин | D11: нет | E11: 44699 | F11: =LEFT(B11,LEN(B11) - 13) -> +7 | G11: Август | H11: Вячеславович | I11: Брагин | J11: {=XLOOKUP(F11,'коды стран'!$B$2:$B$7,'коды стран'!$A$2:$A$7)} -> Россия
A12: 495 | B12: +998 006-788-9211 | C12: Мефодий Филиппович Воробьев | D12: да | E12: 44654 | F12: =LEFT(B12,LEN(B12) - 13) -> +998 | G12: Мефодий | H12: Филиппович | I12: Воробьев | J12: {=XLOOKUP(F12,'коды стран'!$B$2:$B$7,'коды стран'!$A$2:$A$7)} -> Узбекистан
A13: 353 | B13: +992 863-895-4307 | C13: Гурьев Влас Юлианович | D13: да | E13: 44656 | F13: =LEFT(B13,LEN(B13) - 13) -> +992 | G13: Влас | H13: Юлианович | I13: Гурьев | J13: {=XLOOKUP(F13,'коды стран'!$B$2:$B$7,'коды стран'!$A$2:$A$7)} -> Таджикистан
... A435: 427 | B435: +7 630-011-3417 | C435: Лидия Андреевна Крюкова | D435: нет | E435: 44834 | F435: =LEFT(B435,LEN(B435) - 13) -> +7 | G435: Лидия | H435: Андреевна | I435: Крюкова | J435: {=XLOOKUP(F435,'коды стран'!$B$2:$B$7,'коды стран'!$A$2:$A$7)} -> Россия

Sheet Частотность имен
A3: Названия строк | B3: Количество по полю Столбец1
A4: Алевтина | B4: 6
A5: Феврония | B5: 6
A6: Василиса | B6: 6
A7: Любовь | B7: 5
A8: Эмилия | B8: 5
A9: Юлия | B9: 5
A10: Марфа | B10: 5
A11: Вера | B11: 5
A12: Жанна | B12: 5
A13: Лора | B13: 4
A14: Татьяна | B14: 4
A15: Любомир | B15: 4
... A238: Ефрем | B238: 1

Sheet коды стран
A1: Страна | B1: Код
A2: Россия | B2: +7
A3: Казахстан | B3: +7
A4: Беларусь | B4: +375
A5: Узбекистан | B5: +998
A6: Таджикистан | B6: +992
A7: Украина | B7: +380
